blue_sbc/README.py
blue_sbc/__init__.py
blue_sbc/__main__.py
blue_sbc/config.env
blue_sbc/env.py
blue_sbc/host.py
blue_sbc/logger.py
blue_sbc/sample.env
blue_sbc/urls.py
blue_sbc/.abcli/abcli.sh
blue_sbc/.abcli/actions.sh
blue_sbc/.abcli/adafruit_rgb_matrix.sh
blue_sbc/.abcli/alias.sh
blue_sbc/.abcli/blue_sbc.sh
blue_sbc/.abcli/camera.sh
blue_sbc/.abcli/grove.sh
blue_sbc/.abcli/hat.sh
blue_sbc/.abcli/lepton.sh
blue_sbc/.abcli/scroll_phat_hd.sh
blue_sbc/.abcli/session.sh
blue_sbc/.abcli/sparkfun_top_phat.sh
blue_sbc/.abcli/unicorn_16x16.sh
blue_sbc/.abcli/install/adafruit_rgb_matrix.sh
blue_sbc/.abcli/install/grove.sh
blue_sbc/.abcli/install/lepton.sh
blue_sbc/.abcli/install/rpi.sh
blue_sbc/.abcli/install/scroll_phat_hd.sh
blue_sbc/.abcli/install/sparkfun_top_phat.sh
blue_sbc/.abcli/install/template.sh
blue_sbc/.abcli/install/unicorn_16x16.sh
blue_sbc/.abcli/tests/README.sh
blue_sbc/.abcli/tests/camera.sh
blue_sbc/.abcli/tests/help.sh
blue_sbc/.abcli/tests/version.sh
blue_sbc/algo/__init__.py
blue_sbc/algo/diff.py
blue_sbc/hardware/__init__.py
blue_sbc/hardware/adafruit_rgb_matrix.py
blue_sbc/hardware/display.py
blue_sbc/hardware/grove.py
blue_sbc/hardware/hardware.py
blue_sbc/hardware/screen.py
blue_sbc/hardware/scroll_phat_hd.py
blue_sbc/hardware/unicorn_16x16.py
blue_sbc/hardware/hat/__init__.py
blue_sbc/hardware/hat/__main__.py
blue_sbc/hardware/hat/abstract.py
blue_sbc/hardware/hat/prototype.py
blue_sbc/hardware/sparkfun_top_phat/__init__.py
blue_sbc/hardware/sparkfun_top_phat/__main__.py
blue_sbc/hardware/sparkfun_top_phat/classes.py
blue_sbc/help/__init__.py
blue_sbc/help/__main__.py
blue_sbc/help/adafruit_rgb_matrix.py
blue_sbc/help/camera.py
blue_sbc/help/functions.py
blue_sbc/help/grove.py
blue_sbc/help/hat.py
blue_sbc/help/lepton.py
blue_sbc/help/scroll_phat_hd.py
blue_sbc/help/session.py
blue_sbc/help/sparkfun_top_phat.py
blue_sbc/help/unicorn_16x16.py
blue_sbc/imager/__init__.py
blue_sbc/imager/classes.py
blue_sbc/imager/camera/__init__.py
blue_sbc-7.72.1.dist-info/LICENSE
blue_sbc-7.72.1.dist-info/METADATA
blue_sbc-7.72.1.dist-info/WHEEL
blue_sbc-7.72.1.dist-info/top_level.txt
blue_sbc-7.72.1.dist-info/RECORD
